HISTORY.txt
README.txt
TODO.txt
setup.cfg
setup.py
prdg/__init__.py
prdg.zope.permissions.egg-info/PKG-INFO
prdg.zope.permissions.egg-info/SOURCES.txt
prdg.zope.permissions.egg-info/dependency_links.txt
prdg.zope.permissions.egg-info/entry_points.txt
prdg.zope.permissions.egg-info/namespace_packages.txt
prdg.zope.permissions.egg-info/not-zip-safe
prdg.zope.permissions.egg-info/requires.txt
prdg.zope.permissions.egg-info/top_level.txt
prdg/zope/__init__.py
prdg/zope/permissions.py