Metadata-Version: 1.0
Name: prdg.zope.permissions
Version: 0.0.1
Summary: An user-friendlier API for roles and permissions on Zope.
Home-page: UNKNOWN
Author: Rafael Oliveira
Author-email: rafaelbco@gmail.com
License: GPL
Keywords: zope zope2 permissions security
Platform: UNKNOWN
Classifier: Programming Language :: Python
Classifier: Topic :: Software Development :: Libraries :: Python Modules
